a_max_product_lmt/__init__.py
a_max_product_lmt/about.py
a_max_product_lmt/product1.py
a_max_product_lmt/product10.py
a_max_product_lmt/product2.py
a_max_product_lmt/product3.py
a_max_product_lmt/product4.py
a_max_product_lmt/product5.py
a_max_product_lmt/product6.py
a_max_product_lmt/product7.py
a_max_product_lmt/product8.py
a_max_product_lmt/product9.py
a_max_product_lmt-0.1.0.dist-info/licenses/LICENSE
a_max_product_lmt-0.1.0.dist-info/METADATA
a_max_product_lmt-0.1.0.dist-info/WHEEL
a_max_product_lmt-0.1.0.dist-info/top_level.txt
a_max_product_lmt-0.1.0.dist-info/RECORD
