Metadata-Version: 2.4
Name: a_max_product_lmt
Version: 0.1.0
Summary: A package containing company information and 10 products.
Home-page: https://github.com/Avinash8055/
Author: Avinash S
Author-email: Avinash S <avinash.s@gmail.com>
License: MIT License
Project-URL: Homepage, https://github.com/yourusername/companyname
Requires-Python: >=3.7
License-File: LICENSE
Dynamic: author
Dynamic: home-page
Dynamic: license-file
Dynamic: requires-python
